classification/__init__.py
classification/classification.py
classification/classification_metrics.py
classification/plot.py
regression/__init__.py
regression/plot.py
regression/regression.py
regression/regression_metrics.py
simplysklearn/__init__.py
simplysklearn/classification/__init__.py
simplysklearn/classification/classification.py
simplysklearn/classification/classification_metrics.py
simplysklearn/classification/plot.py
simplysklearn/regression/__init__.py
simplysklearn/regression/plot.py
simplysklearn/regression/regression.py
simplysklearn/regression/regression_metrics.py
simplysklearn-0.2.4.dist-info/LICENSE
simplysklearn-0.2.4.dist-info/METADATA
simplysklearn-0.2.4.dist-info/WHEEL
simplysklearn-0.2.4.dist-info/top_level.txt
simplysklearn-0.2.4.dist-info/RECORD
