Metadata-Version: 2.1
Name: simplysklearn
Version: 0.2.4
Summary: Python package to automate machine learning process to showcase metric values for nearly all Scikit-Learn's models.
Home-page: https://github.com/vanilladucky/simplysklearn
Author: Kim Hyun Bin
Author-email: KIMH0004@e.ntu.edu.sg
Classifier: Programming Language :: Python :: 3
Classifier: License :: OSI Approved :: MIT License
Classifier: Operating System :: OS Independent
Requires-Python: >=3
License-File: LICENSE
Requires-Dist: numpy
Requires-Dist: pandas
Requires-Dist: scikit-learn
Requires-Dist: seaborn
Requires-Dist: matplotlib
Requires-Dist: tqdm
Requires-Dist: xgboost
